[
  {
    "Id": 2001,
    "shape": [
      0,
      0,
      0,
      0,
      0,
      0,
      0,
      0,
      0,
      0,
      1,
      1,
      1,
      1,
      0,
      0,
      0,
      0,
      0,
      0,
      0,
      0,
      0,
      0,
      0
    ],
    "can_be_attack": true,
    "props": [
      [
        10011,
        200000
      ],
      [
        10041,
        10000
      ]
    ]
  },
  {
    "Id": 2002,
    "shape": [
      0,
      0,
      1,
      0,
      0,
      0,
      0,
      1,
      0,
      0,
      0,
      0,
      1,
      0,
      0,
      0,
      0,
      1,
      0,
      0,
      0,
      0,
      0,
      0,
      0
    ],
    "can_be_attack": true,
    "props": [
      [
        10011,
        200000
      ],
      [
        10041,
        10000
      ]
    ]
  },
  {
    "Id": 2003,
    "shape": [
      0,
      0,
      0,
      0,
      0,
      0,
      0,
      1,
      0,
      0,
      0,
      0,
      1,
      0,
      0,
      0,
      1,
      1,
      1,
      0,
      0,
      0,
      0,
      0,
      0
    ],
    "can_be_attack": true,
    "props": [
      [
        10011,
        200000
      ],
      [
        10041,
        10000
      ]
    ]
  }
]