[
  {
    "Id": 2001,
    "desc": "横一字型",
    "model": 20010001,
    "placed_layer": 3,
    "shape": [
      false,
      false,
      false,
      false,
      false,
      false,
      false,
      false,
      false,
      false,
      true,
      true,
      true,
      true,
      false,
      false,
      false,
      false,
      false,
      false,
      false,
      false,
      false,
      false,
      false
    ],
    "can_be_attack": true,
    "props": [
      [
        10011,
        200000
      ],
      [
        10041,
        10000
      ]
    ],
    "skills": [
      20010001
    ]
  },
  {
    "Id": 2002,
    "desc": "竖一字型",
    "model": 20020001,
    "placed_layer": 3,
    "shape": [
      false,
      false,
      true,
      false,
      false,
      false,
      false,
      true,
      false,
      false,
      false,
      false,
      true,
      false,
      false,
      false,
      false,
      true,
      false,
      false,
      false,
      false,
      false,
      false,
      false
    ],
    "can_be_attack": true,
    "props": [
      [
        10011,
        200000
      ],
      [
        10041,
        10000
      ]
    ],
    "skills": []
  },
  {
    "Id": 2003,
    "desc": "T字形",
    "model": 20030001,
    "placed_layer": 3,
    "shape": [
      false,
      false,
      false,
      false,
      false,
      false,
      false,
      true,
      false,
      false,
      false,
      false,
      true,
      false,
      false,
      false,
      true,
      true,
      true,
      false,
      false,
      false,
      false,
      false,
      false
    ],
    "can_be_attack": true,
    "props": [
      [
        10011,
        200000
      ],
      [
        10041,
        10000
      ]
    ],
    "skills": []
  }
]